narcissistic/narcissistic.py
narcissistic-1.3.dist-info/LICENSE
narcissistic-1.3.dist-info/METADATA
narcissistic-1.3.dist-info/WHEEL
narcissistic-1.3.dist-info/top_level.txt
narcissistic-1.3.dist-info/RECORD
